relayer/__init__.py
relayer/event_emitter.py
relayer/exceptions.py
relayer/logger.py
relayer/logging.py
relayer/flask/__init__.py
relayer/rpc/__init__.py
relayer/test/__init__.py
relayer/test/mocked_producer.py
relayer/test/relayer_patch.py
relayer/utils/__init__.py
relayer-2.0.2.dist-info/METADATA
relayer-2.0.2.dist-info/RECORD
relayer-2.0.2.dist-info/WHEEL
relayer-2.0.2.dist-info/top_level.txt
