Metadata-Version: 2.1
Name: relayer
Version: 2.0.2
Summary: Relayer is a library to emit kafka messages and group logs to relay them to kafka for log aggregation.
Home-page: https://github.com/wizeline/relayer
Author: Wizeline
Author-email: engineering@wizeline.com
License: UNKNOWN
Keywords: relayer,log,kafka
Platform: UNKNOWN
Classifier: Development Status :: 4 - Beta
Classifier: License :: OSI Approved :: MIT License
Classifier: Intended Audience :: Developers
Classifier: Natural Language :: English
Classifier: Programming Language :: Python :: 3
Requires-Dist: kafka-python (==1.3.4)
Requires-Dist: structlog (>=17.2.0)
